design.sv
`timescale 1ns / 1ns

module TestBench ();
	logic clk, reset, write_to_memory;
	logic [31:0] write_data, data_address;

	// instantiates device under test (top level module)
	Top dut (
		clk,
		reset,
		write_to_memory,
		write_data,
		data_address
	);

	// initializes test
	initial begin
		reset <= 1;
		#22;		// 2.2 cycles
		reset <= 0;
	end

	// generates clock
	initial begin
	        clk <= 0;
	        forever #5 clk = ~clk;		// 5ns high + 5ns low = 10ns → 100MHz
	end

	initial begin
		$dumpfile("waveform.vcd");		// indicates file.vcd (Value Change Dump)
		$dumpvars(0, dut);				// dump signals from the module

		#500;
		// $dumpon;
		// $dumpoff;
		$finish;
	end

	// checks results
	always @(negedge clk) begin
		if (write_to_memory) begin
			if (data_address === 100 & write_data === 25) begin
					$display("Simulation succeeded!");
					$stop;
			end
			else if (data_address !== 96) begin
					$display("Simulation failed!");
					$stop;
			end
		end
	end
endmodule

// top level module
module Top (  
		input logic clk, reset,
		output logic write_to_memory,
		output logic [31:0] write_data,
		data_address
);

	logic [31:0] PC, instruction, data_read;

	// instantiate processor and memories
	Processor riscvsingle (
		clk,
		reset,
		instruction,
		data_read,
		write_to_memory,
		PC,
		data_address,
		write_data
	);

	InstructionMemory instMemory (
		PC,
		instruction
	);

	DataMemory dataMemory (
		clk,
		write_to_memory,
		data_address,
		write_data,
		data_read
	);
endmodule

module Processor (
		input logic clk, reset,
		input logic [31:0] instruction,
		data_read,
		output logic write_to_memory,
		output logic [31:0] PC,
		ALU_result,		// data_address
		write_data
);
	logic ALU_source, write_to_register, jump, zero, PC_source;
	logic [1:0] result_source, immediate_source;
	logic [2:0] ALU_control;

	Controller controller (
		instruction[30],
		zero,
		instruction[14:12],
		instruction[6:0],
		write_to_memory,
		PC_source,
		ALU_source,
		write_to_register,
		jump,
		result_source,
		immediate_source,
		ALU_control
	);

	Datapath datapath (
		clk,
		reset,
		PC_source,
		ALU_source,
		write_to_register,
		result_source,
		immediate_source,
		ALU_control,
		instruction,
		data_read,
		zero,
		PC,
		write_data,
		ALU_result
	);
endmodule

module InstructionMemory (
		input  logic [31:0] address,		// program counter
		output logic [31:0] instruction_read		// fetched instruction
);
	logic [31:0] RAM[0:63];		// 64 x 32-bit instruction memory

	initial $readmemh("instructions.hex", RAM);		// load instructions from file

	assign instruction_read = RAM[address[31:2]];		// word-aligned access (bit slicing)

	final begin
		$writememh("./dump/instructionMemory.hex", RAM);		// dump memory contents to a file at the end of simulation
	end
endmodule

module DataMemory (
		input logic clk,
		write_enabled,
		input logic [31:0] address,
		data_to_write,		// data to write
		output logic [31:0] data_read		// data read
);

	logic [31:0] RAM[0:63];		// 64 x 32-bit words

	assign data_read = RAM[address[31:2]];		// word-aligned read

	always_ff @(posedge clk)
		if (write_enabled)
			RAM[address[31:2]] <= data_to_write;		// word-aligned write

	final begin
		$writememh("./dump/dataMemory.hex", RAM);		// dump memory contents to a file at the end of simulation
	end
endmodule

module Controller (
		input logic funct7_b5,
		zero,
		input logic [2:0] funct3,
		input logic [6:0] opcode,
		output logic write_to_memory,
		PC_source,
		ALU_source,
		write_to_register,
		jump,
		output logic [1:0] result_source,
		output logic [1:0] immediate_source,
		output logic [2:0] ALU_control
);

	logic branch;
	logic [1:0] ALU_operation;

	MainDecoder maindecoder (
		opcode,
		write_to_memory,
		branch,
		ALU_source,
		write_to_register,
		jump,
		result_source,
		immediate_source,
		ALU_operation
	);

	ALUDecoder ALUdecoder (
		opcode[5],
		funct7_b5,
		ALU_operation,
		funct3,
		ALU_control
	);

	assign PC_source = branch & zero;
endmodule

module MainDecoder (
		input logic [6:0] opcode,
		output logic write_to_memory,
		branch,
		ALU_source,
		write_to_register,
		jump,
		output logic [1:0] result_source,
		immediate_source,
		ALU_operation
);
	logic [10:0] controls;

	always_comb begin
		case (opcode)
			7'b0000011:
				controls = 11'b1_00_1_0_01_0_00_0;	// lw
			7'b0100011:
				controls = 11'b0_01_1_1_00_0_00_0;	// sw
			7'b0110011:
				controls = 11'b1_xx_0_0_00_0_10_0;	// R-type
			7'b1100011:
				controls = 11'b0_10_0_0_00_1_01_0;	// beq
			default:
				controls = 11'bx_xx_x_x_xx_x_xx_x;	// non-implemented instruction
		endcase
	end

	// splits the control vector into individual signals
	assign {write_to_register, immediate_source, ALU_source, write_to_memory, result_source, branch, ALU_operation, jump} = controls;
endmodule

module ALUDecoder (
		input logic opcode_b5,
		funct7_b5,
		input logic [1:0] ALU_operation,
		input logic [2:0] funct3,
		output logic [2:0] ALU_control
);
	logic is_rtype_sub;
	assign is_rtype_sub = funct7_b5 & opcode_b5;		// TRUE for R-type subtract instruction

	always_comb
		case (ALU_operation)
			2'b00:
				ALU_control = 3'b000;		// addition
			2'b01:
				ALU_control = 3'b001;		// subtraction
			default:
				case (funct3)		// R-type or I-type ALU
					3'b000:
						if (is_rtype_sub)
							ALU_control = 3'b001;		// sub
						else
							ALU_control = 3'b000;		// add, addi
					3'b010:
						ALU_control = 3'b101;		// slt, slti
					3'b110:
						ALU_control = 3'b011;		// or, ori
					3'b111:
						ALU_control = 3'b010;		// and, andi
					default:
						ALU_control = 3'bxxx;		// ???
				endcase
		endcase
endmodule

module Datapath (
	input logic clk, reset,
	PC_source,
	ALU_source,
	RegWrite,
	input logic [ 1:0] result_source,
	immediate_source,
	input logic [ 2:0] ALU_control,
	input logic [31:0] instruction,
	data_read,
	output logic zero,
	output logic [31:0] PC,
	write_data,
	ALU_result
);
	logic [31:0] PC_next, PC_plus4, PC_target;
	logic [31:0] immediate_extended;		// ¿ de onde vem ?
	logic [31:0] source_A, source_B;
	logic [31:0] result;

	// next program counter logic
	FlipFlopR #(32) PCregister (
		clk, reset,
		PC_next,
		PC
	);

	Adder PC_plus4_adder  (
		PC,
		32'd4,
		PC_plus4
	);

	Adder PC_branch_adder (
		PC,
		immediate_extended,
		PC_target
	);
	
	Mux2to1 #(32) PCmux (
		PC_plus4, PC_target,
		PC_source,
		PC_next
	);

	logic TEST_source;
	logic [31:0] TEST_output;

	initial begin
		TEST_source <= 0;
	        forever #5 TEST_source = ~TEST_source;
	end

	MuxNto1 #(32, 2) PCmux2 (
		.in({PC_target, PC_plus4}),
		.sel(TEST_source),
		.out(TEST_output)
	);

	/*
	// // register file logic
	// regfile rf (
	// 		clk,
	// 		RegWrite,
	// 		Instr[19:15],
	// 		Instr[24:20],
	// 		Instr[11:7],
	// 		Result,
	// 		SrcA,
	// 		WriteData
	// );

	// extend ext (
	// 		Instr[31:7],
	// 		ImmSrc,
	// 		ImmExt
	// );
	*/

	// ALU logic
	// mux2 #(32) srcbmux (
	// 		WriteData,
	// 		ImmExt,
	// 		ALUSrc,
	// 		SrcB
	// );
	// alu alu (
	// 		SrcA,
	// 		SrcB,
	// 		ALUControl,
	// 		ALUResult,
	// 		Zero
	// );
	// mux3 #(32) resultmux (
	// 		ALUResult,
	// 		ReadData,
	// 		32'b0,
	// 		ResultSrc,
	// 		Result
	// );
endmodule

module FlipFlopR #(
		parameter WIDTH = 8
) (
		input logic clk, reset,
		input logic [WIDTH-1:0] d,
		output logic [WIDTH-1:0] q
);
	always_ff @(posedge clk, posedge reset) begin
		if (reset)
			q <= 0;
		else
			q <= d;
	end
endmodule

module Adder (
		input  logic [31:0] a, b,
		output logic [31:0] sum
);
	assign sum = a + b;
endmodule

module Mux2to1 #(
		parameter WIDTH = 8
) (
		input  logic [WIDTH-1:0] in0, in1,
		input  logic             sel,
		output logic [WIDTH-1:0] out
);
	assign out = sel ? in1 : in0;
endmodule

module Mux3to1 #(
		parameter WIDTH = 8
) (
		input  logic [WIDTH-1:0] in0, in1, in2,
		input  logic [      1:0] sel,
		output logic [WIDTH-1:0] out
);
	assign out = sel[1] ? in2 : (sel[0] ? in1 : in0);
endmodule

module MuxNto1 #(
	parameter WIDTH = 32,
	parameter N     = 4
)(
    input  logic [N-1:0][WIDTH-1:0] in,		// inputs
    input  logic [$clog2(N)-1:0] sel,		// selector
    output logic [WIDTH-1:0] out
);
    always_comb begin
        out = in[sel];
    end
endmodule

// module regfile (
// 		input  logic        clk,
// 		input  logic        we3,
// 		input  logic [ 4:0] a1,
// 		a2,
// 		a3,
// 		input  logic [31:0] wd3,
// 		output logic [31:0] rd1,
// 		rd2
// );
// 	logic [31:0] rf[31:0];  // 32 registers, each 32 bits wide

// 	// Three-ported register file:
// 	// - Two ports for combinational reads (A1/RD1, A2/RD2)
// 	// - One port for clocked writes (A3/WD3/WE3)
// 	// - Register 0 is hardwired to 0

// 	always_ff @(posedge clk) begin
// 		if (we3) rf[a3] <= wd3;
// 	end

// 	assign rd1 = (a1 != 0) ? rf[a1] : 0;  // Return 0 if accessing register 0
// 	assign rd2 = (a2 != 0) ? rf[a2] : 0;  // Return 0 if accessing register 0
// endmodule

// module extend (
// 		input  logic [31:7] instr,
// 		input  logic [ 1:0] immsrc,
// 		output logic [31:0] immext
// );

// 	always_comb begin
// 		case (immsrc)
// 			// B-type (branches)
// 			2'b01: immext = {{20{instr[31]}}, instr[31:25], instr[11:7]};

// 			// J-type (jumps)
// 			2'b11: immext = {{12{instr[31]}}, instr[19:12], instr[20], instr[30:21], 1'b0};

// 			// Undefined cases
// 			default: immext = 32'bx;
// 		endcase
// 	end
// endmodule

// module alu (
// 		input  logic [31:0] a,
// 		b,
// 		input  logic [ 2:0] alucontrol,
// 		output logic [31:0] result,
// 		output logic        zero
// );

// 	logic [31:0] condinvb, sum;
// 	logic v;  // Overflow flag
// 	logic isAddSub;  // True for add or subtract operations

// 	// Prepare conditional inversion of 'b' and calculate sum
// 	assign condinvb = alucontrol[0] ? ~b : b;
// 	assign sum = a + condinvb + alucontrol[0];

// 	// Determine if the operation is addition or subtraction
// 	assign isAddSub = ~alucontrol[2] & ~alucontrol[1] | ~alucontrol[1] & alucontrol[0];

// 	// ALU operation
// 	always_comb begin
// 		case (alucontrol)
// 			3'b000:  result = sum;  // Add
// 			3'b001:  result = sum;  // Subtract
// 			3'b010:  result = a & b;  // AND
// 			3'b011:  result = a | b;  // OR
// 			3'b100:  result = a ^ b;  // XOR
// 			3'b101:  result = sum[31] ^ v;  // SLT (set less than)
// 			3'b110:  result = a << b[4:0];  // SLL (shift left logical)
// 			3'b111:  result = a >> b[4:0];  // SRL (shift right logical)
// 			default: result = 32'bx;  // Undefined operation
// 		endcase
// 	end

// 	// Zero flag: true if result is zero
// 	assign zero = (result == 32'b0);

// 	// Overflow detection
// 	assign v = ~(alucontrol[0] ^ a[31] ^ b[31]) & (a[31] ^ sum[31]) & isAddSub;
// endmodule

waveform.vcd
$date
	Tue Apr  8 23:18:48 2025
$end
$version
	Icarus Verilog
$end
$timescale
	1ns
$end
$scope module TestBench $end
$scope module dut $end
$var wire 1 ! clk $end
$var wire 1 " reset $end
$var wire 1 # write_to_memory $end
$var wire 32 $ write_data [31:0] $end
$var wire 32 % instruction [31:0] $end
$var wire 32 & data_read [31:0] $end
$var wire 32 ' data_address [31:0] $end
$var wire 32 ( PC [31:0] $end
$scope module dataMemory $end
$var wire 1 ! clk $end
$var wire 32 ) data_read [31:0] $end
$var wire 1 # write_enabled $end
$var wire 32 * data_to_write [31:0] $end
$var wire 32 + address [31:0] $end
$upscope $end
$scope module instMemory $end
$var wire 32 , instruction_read [31:0] $end
$var wire 32 - address [31:0] $end
$upscope $end
$scope module riscvsingle $end
$var wire 1 ! clk $end
$var wire 32 . data_read [31:0] $end
$var wire 32 / instruction [31:0] $end
$var wire 1 " reset $end
$var wire 1 0 zero $end
$var wire 1 1 write_to_register $end
$var wire 1 # write_to_memory $end
$var wire 32 2 write_data [31:0] $end
$var wire 2 3 result_source [1:0] $end
$var wire 1 4 jump $end
$var wire 2 5 immediate_source [1:0] $end
$var wire 1 6 PC_source $end
$var wire 32 7 PC [31:0] $end
$var wire 1 8 ALU_source $end
$var wire 32 9 ALU_result [31:0] $end
$var wire 3 : ALU_control [2:0] $end
$scope module controller $end
$var wire 1 6 PC_source $end
$var wire 3 ; funct3 [2:0] $end
$var wire 1 < funct7_b5 $end
$var wire 7 = opcode [6:0] $end
$var wire 1 0 zero $end
$var wire 1 1 write_to_register $end
$var wire 1 # write_to_memory $end
$var wire 2 > result_source [1:0] $end
$var wire 1 4 jump $end
$var wire 2 ? immediate_source [1:0] $end
$var wire 1 @ branch $end
$var wire 1 8 ALU_source $end
$var wire 2 A ALU_operation [1:0] $end
$var wire 3 B ALU_control [2:0] $end
$scope module ALUdecoder $end
$var wire 3 C funct3 [2:0] $end
$var wire 1 < funct7_b5 $end
$var wire 1 D is_rtype_sub $end
$var wire 1 E opcode_b5 $end
$var wire 2 F ALU_operation [1:0] $end
$var reg 3 G ALU_control [2:0] $end
$upscope $end
$scope module maindecoder $end
$var wire 7 H opcode [6:0] $end
$var wire 1 1 write_to_register $end
$var wire 1 # write_to_memory $end
$var wire 2 I result_source [1:0] $end
$var wire 1 4 jump $end
$var wire 2 J immediate_source [1:0] $end
$var wire 1 @ branch $end
$var wire 1 8 ALU_source $end
$var wire 2 K ALU_operation [1:0] $end
$var reg 11 L controls [10:0] $end
$upscope $end
$upscope $end
$scope module datapath $end
$var wire 3 M ALU_control [2:0] $end
$var wire 1 8 ALU_source $end
$var wire 1 6 PC_source $end
$var wire 1 1 RegWrite $end
$var wire 1 ! clk $end
$var wire 32 N data_read [31:0] $end
$var wire 2 O immediate_source [1:0] $end
$var wire 32 P instruction [31:0] $end
$var wire 1 " reset $end
$var wire 2 Q result_source [1:0] $end
$var wire 32 R TEST_output [31:0] $end
$var wire 32 S PC_target [31:0] $end
$var wire 32 T PC_plus4 [31:0] $end
$var wire 32 U PC_next [31:0] $end
$var wire 32 V PC [31:0] $end
$var reg 32 W ALU_result [31:0] $end
$var reg 1 X TEST_source $end
$var reg 32 Y immediate_extended [31:0] $end
$var reg 32 Z write_data [31:0] $end
$var reg 1 0 zero $end
$scope module PC_branch_adder $end
$var wire 32 [ b [31:0] $end
$var wire 32 \ sum [31:0] $end
$var wire 32 ] a [31:0] $end
$upscope $end
$scope module PC_plus4_adder $end
$var wire 32 ^ b [31:0] $end
$var wire 32 _ sum [31:0] $end
$var wire 32 ` a [31:0] $end
$upscope $end
$scope module PCmux $end
$var wire 32 a in0 [31:0] $end
$var wire 32 b in1 [31:0] $end
$var wire 1 6 sel $end
$var wire 32 c out [31:0] $end
$var parameter 32 d WIDTH $end
$upscope $end
$scope module PCmux2 $end
$var wire 64 e in [63:0] $end
$var wire 1 X sel $end
$var parameter 32 f N $end
$var parameter 32 g WIDTH $end
$var reg 32 h out [31:0] $end
$upscope $end
$scope module PCregister $end
$var wire 1 ! clk $end
$var wire 32 i d [31:0] $end
$var wire 1 " reset $end
$var parameter 32 j WIDTH $end
$var reg 32 k q [31:0] $end
$upscope $end
$upscope $end
$upscope $end
$upscope $end
$upscope $end
$enddefinitions $end
$comment Show the parameter values. $end
$dumpall
b100000 j
b100000 g
b10 f
b100000 d
$end
#0
$dumpvars
b0 k
bx i
b100 h
bx00000000000000000000000000000100 e
bx c
bx b
b100 a
b0 `
b100 _
b100 ^
b0 ]
bx \
bx [
bx Z
bx Y
0X
bx W
b0 V
bx U
b100 T
bx S
b100 R
bx Q
b10100000000000100010011 P
bx O
bx N
b0 M
bx L
bx K
bx J
bx I
b10011 H
b0 G
bx F
0E
0D
b0 C
b0 B
bx A
x@
bx ?
bx >
b10011 =
0<
b0 ;
b0 :
bx 9
x8
b0 7
x6
bx 5
x4
bx 3
bx 2
x1
x0
b10100000000000100010011 /
bx .
b0 -
b10100000000000100010011 ,
bx +
bx *
bx )
b0 (
bx '
bx &
b10100000000000100010011 %
bx $
x#
1"
0!
$end
#5
bx R
bx h
1!
1X
#10
b100 R
b100 h
0!
0X
#15
bx R
bx h
1!
1X
#20
b100 R
b100 h
0!
0X
#22
0"
#25
xD
bx :
bx B
bx G
bx M
xE
x<
bx ;
bx C
bx =
bx H
bx %
bx ,
bx /
bx P
bx e
bx T
bx _
bx a
bx (
bx -
bx 7
bx V
bx ]
bx `
bx k
bx R
bx h
1!
1X
#30
0!
0X
#35
1!
1X
#40
0!
0X
#45
1!
1X
#50
0!
0X
#55
1!
1X
#60
0!
0X
#65
1!
1X
#70
0!
0X
#75
1!
1X
#80
0!
0X
#85
1!
1X
#90
0!
0X
#95
1!
1X
#100
0!
0X
#105
1!
1X
#110
0!
0X
#115
1!
1X
#120
0!
0X
#125
1!
1X
#130
0!
0X
#135
1!
1X
#140
0!
0X
#145
1!
1X
#150
0!
0X
#155
1!
1X
#160
0!
0X
#165
1!
1X
#170
0!
0X
#175
1!
1X
#180
0!
0X
#185
1!
1X
#190
0!
0X
#195
1!
1X
#200
0!
0X
#205
1!
1X
#210
0!
0X
#215
1!
1X
#220
0!
0X
#225
1!
1X
#230
0!
0X
#235
1!
1X
#240
0!
0X
#245
1!
1X
#250
0!
0X
#255
1!
1X
#260
0!
0X
#265
1!
1X
#270
0!
0X
#275
1!
1X
#280
0!
0X
#285
1!
1X
#290
0!
0X
#295
1!
1X
#300
0!
0X
#305
1!
1X
#310
0!
0X
#315
1!
1X
#320
0!
0X
#325
1!
1X
#330
0!
0X
#335
1!
1X
#340
0!
0X
#345
1!
1X
#350
0!
0X
#355
1!
1X
#360
0!
0X
#365
1!
1X
#370
0!
0X
#375
1!
1X
#380
0!
0X
#385
1!
1X
#390
0!
0X
#395
1!
1X
#400
0!
0X
#405
1!
1X
#410
0!
0X
#415
1!
1X
#420
0!
0X
#425
1!
1X
#430
0!
0X
#435
1!
1X
#440
0!
0X
#445
1!
1X
#450
0!
0X
#455
1!
1X
#460
0!
0X
#465
1!
1X
#470
0!
0X
#475
1!
1X
#480
0!
0X
#485
1!
1X
#490
0!
0X
#495
1!
1X
#500
0!
0X
